tfcat/__init__.py
tfcat/_version.py
tfcat/base.py
tfcat/codec.py
tfcat/crs.py
tfcat/factory.py
tfcat/feature.py
tfcat/field.py
tfcat/geometry.py
tfcat/observation.py
tfcat/tfcat.py
tfcat/utils.py
tfcat/validate.py
tfcat-1.0.3.dist-info/licenses/LICENSE
tfcat-1.0.3.dist-info/METADATA
tfcat-1.0.3.dist-info/WHEEL
tfcat-1.0.3.dist-info/top_level.txt
tfcat-1.0.3.dist-info/RECORD
