Metadata-Version: 2.4
Name: TFCat
Version: 1.0.3
Summary: Time-Frequency Catalogue (TFCat) Python module.
Author-email: Baptiste Cecconi <baptiste.cecconi@obspm.fr>, Xavier Bonnin <xavier.bonnin@obspm.fr>, Alan Loh <alan.loh@obspm.fr>, Adam Boudouma <adam.boudouma@obspm.fr>
License-Expression: MIT
Project-URL: Homepage, https://gitlab.obspm.fr/maser/catalogues/tfcat
Project-URL: Bug Tracker, https://gitlab.obspm.fr/maser/catalogues/tfcat/-/issues
Keywords: radio astronomy,catalogue
Classifier: Programming Language :: Python :: 3
Classifier: Operating System :: OS Independent
Requires-Python: >=3.7
License-File: LICENSE
Requires-Dist: astropy
Requires-Dist: matplotlib
Requires-Dist: shapely
Requires-Dist: jsonschema
Dynamic: license-file
